pyatag/__init__.py
pyatag/const.py
pyatag/discovery.py
pyatag/entities.py
pyatag/errors.py
pyatag/gateway.py
pyatag-0.3.7.1.dist-info/LICENSE.txt
pyatag-0.3.7.1.dist-info/METADATA
pyatag-0.3.7.1.dist-info/WHEEL
pyatag-0.3.7.1.dist-info/top_level.txt
pyatag-0.3.7.1.dist-info/zip-safe
pyatag-0.3.7.1.dist-info/RECORD
